pyqcolour/__init__.py
pyqcolour/test.py
pyqcolour-1.2.dist-info/METADATA
pyqcolour-1.2.dist-info/WHEEL
pyqcolour-1.2.dist-info/top_level.txt
pyqcolour-1.2.dist-info/RECORD
