Metadata-Version: 2.1
Name: pyqcolour
Version: 1.2
Summary: python library for colors
Author-email: dansecurity@gmail.com
License: Eclipse Public License 2.0
